{
    "$id": "https://schemas.3d.si.edu/voyager/features.schema.json",
    "$schema": "http://json-schema.org/draft-07/schema#",

    "title": "Smithsonian 3D Voyager Feature Components",
    "description": "Settings of feature components (scene environment, UI, tools, etc.)",

    "type": "object",
    "properties": {
        "meta": {
            "$ref": "https://schemas.3d.si.edu/voyager/meta.schema.json"
        },
        "process": {
            "$ref": "https://schemas.3d.si.edu/voyager/process.schema.json"
        },
        "annotations": {
            "$ref": "https://schemas.3d.si.edu/voyager/annotations.schema.json"
        },
        "articles": {
            "$ref": "https://schemas.3d.si.edu/voyager/articles.schema.json"
        },
        "tours": {
            "$ref": "https://schemas.3d.si.edu/voyager/tours.schema.json"
        },
        "scene": {
            "type": "object",
            "properties": {
                "units": {
                    "type": "string",
                    "enum": [
                        "mm", "cm", "m", "in", "ft", "yd"
                    ]
                },
                "shader": {
                    "type": "string"
                },
                "exposure": {
                    "type": "number"
                },
                "gamma": {
                    "type": "number"
                }
            },
            "required": [
                "units",
                "shader",
                "exposure",
                "gamma"
            ]
        },
        "reader": {
            "type": "object",
            "properties": {
                "visible": {
                    "type": "boolean"
                },
                "position": {
                    "type": "string"
                },
                "documentUri": {
                    "description": "URI of the document currently displayed in the reader",
                    "type": "string",
                    "minLength": 1
                }
            }
        },
        "interface": {
            "type": "object",
            "properties": {
                "visible": {
                    "type": "boolean"
                },
                "logo": {
                    "type": "boolean"
                },
                "menu": {
                    "type": "boolean"
                },
                "tools": {
                    "type": "boolean"
                }
            }
        },
        "navigation": {
            "type": "object",
            "properties": {
                "type": {
                    "type": "string",
                    "enum": [
                        "orbit", "walk"
                    ]
                },
                "enabled": {
                    "type": "boolean"
                },
                "orbit": {
                    "$comment": "TODO: Implement",

                    "type": "object",
                    "properties": {

                    }
                },
                "walk": {
                    "$comment": "TODO: Implement",

                    "type": "object",
                    "properties": {
                    }
                }
            }
        },
        "background": {
            "type": "object",
            "properties": {
                "style": {
                    "type": "string",
                    "enum": [
                        "Solid", "LinearGradient", "RadialGradient"
                    ]
                },
                "color0": {
                    "$ref": "math.schema.json#/definitions/vector3"
                },
                "color1": {
                    "$ref": "math.schema.json#/definitions/vector3"
                }
            }
        },
        "floor": {
            "type": "object",
            "properties": {
                "visible": {
                    "type": "boolean"
                },
                "position": {
                    "$ref": "math.schema.json#/definitions/vector3"
                },
                "size": {
                    "type": "number"
                },
                "color": {
                    "$ref": "math.schema.json#/definitions/vector3"
                },
                "opacity": {
                    "type": "number"
                },
                "receiveShadow": {
                    "type": "boolean"
                }
            }
        },
        "grid": {
            "type": "object",
            "properties": {
                "visible": {
                    "type": "boolean"
                },
                "color": {
                    "$ref": "math.schema.json#/definitions/vector3"
                }
            }
        },
        "tapeTool": {
            "type": "object",
            "properties": {
                "enabled": {
                    "type": "boolean"
                },
                "startPosition": {
                    "$ref": "math.schema.json#/definitions/vector3"
                },
                "startDirection": {
                    "$ref": "math.schema.json#/definitions/vector3"
                },
                "endPosition": {
                    "$ref": "math.schema.json#/definitions/vector3"
                },
                "endDirection": {
                    "$ref": "math.schema.json#/definitions/vector3"
                }
            }
        },
        "sectionTool": {
            "type": "object",
            "properties": {
                "enabled": {
                    "type": "boolean"
                },
                "axis": {
                    "type": "string",
                    "enum": [ "X", "Y", "Z" ]
                },
                "inverted": {
                    "type": "boolean"
                },
                "position": {
                    "type": "number"
                }
            }
        }
    }
}
